github_demo/__init__.py
github_demo/cli/__init__.py
github_demo/cli/demo.py
github_demo/main.py
github_demo-0.1.0.dist-info/METADATA
github_demo-0.1.0.dist-info/WHEEL
github_demo-0.1.0.dist-info/entry_points.txt
github_demo-0.1.0.dist-info/RECORD
